azampay/__init__.py
azampay/config.py
azampay/core.py
azampay/exceptions.py
example_usage/__init__.py
example_usage/main.py
tests/__init__.py
tests/test_client.py
azampay_sdk_anga-0.1.14.dist-info/METADATA
azampay_sdk_anga-0.1.14.dist-info/WHEEL
azampay_sdk_anga-0.1.14.dist-info/top_level.txt
azampay_sdk_anga-0.1.14.dist-info/RECORD
