Metadata-Version: 2.4
Name: azampay-sdk-anga
Version: 0.1.14
Summary: A dynamic Python SDK for AzamPay (AzamPay Python SDK used for native python, Django, Flask, FastApi e.t.c)
Home-page: https://github.com/tbwahacker/azampay-sdk-anga
Author: Anganile Adam (Anga)
Author-email: "Anganile Adam (Anga)" <twaloadam@gmail.com>
License: MIT
Project-URL: Homepage, https://github.com/tbwahacker/azampay-sdk-anga
Project-URL: Repository, https://github.com/tbwahacker/azampay-sdk-anga
Keywords: sdk,api client,payments,integration,python
Requires-Python: >=3.6
Requires-Dist: requests
Requires-Dist: python-dotenv
Dynamic: author
Dynamic: home-page
Dynamic: requires-python
